tulit/__init__.py
tulit/client/__init__.py
tulit/client/client.py
tulit/client/eu/cellar.py
tulit/client/eu/queries/__init__.py
tulit/client/eu/queries/formex_eli_query.rq
tulit/client/eu/queries/formex_query.rq
tulit/client/eu/queries/html_query.rq
tulit/client/eu/queries/html_standard_query.rq
tulit/client/regional/veneto.py
tulit/client/state/boe.py
tulit/client/state/finlex.py
tulit/client/state/germany.py
tulit/client/state/irishstatutebook.py
tulit/client/state/legifrance.py
tulit/client/state/legilux.py
tulit/client/state/malta.py
tulit/client/state/normattiva.py
tulit/client/state/portugal.py
tulit/parser/__init__.py
tulit/parser/exceptions.py
tulit/parser/html/__init__.py
tulit/parser/html/cellar/__init__.py
tulit/parser/html/cellar/cellar.py
tulit/parser/html/cellar/cellar_standard.py
tulit/parser/html/cellar/proposal.py
tulit/parser/html/html_parser.py
tulit/parser/html/veneto.py
tulit/parser/json/__init__.py
tulit/parser/json/legifrance.py
tulit/parser/legaljson_schema.json
tulit/parser/models.py
tulit/parser/normalization.py
tulit/parser/parser.py
tulit/parser/registry.py
tulit/parser/strategies/__init__.py
tulit/parser/strategies/article_extraction.py
tulit/parser/xml/__init__.py
tulit/parser/xml/akomantoso/__init__.py
tulit/parser/xml/akomantoso/akn4eu.py
tulit/parser/xml/akomantoso/base.py
tulit/parser/xml/akomantoso/extractors.py
tulit/parser/xml/akomantoso/german.py
tulit/parser/xml/akomantoso/luxembourg.py
tulit/parser/xml/akomantoso/utils.py
tulit/parser/xml/assets/akomantoso30.xsd
tulit/parser/xml/assets/eli.owl
tulit/parser/xml/assets/formex4.xsd
tulit/parser/xml/assets/import/xml.xsd
tulit/parser/xml/assets/subdivisions.xml
tulit/parser/xml/assets/xml.xsd
tulit/parser/xml/boe.py
tulit/parser/xml/formex.py
tulit/parser/xml/helpers.py
tulit/parser/xml/xml.py
tulit-0.4.4.dist-info/LICENSE
tulit-0.4.4.dist-info/METADATA
tulit-0.4.4.dist-info/WHEEL
tulit-0.4.4.dist-info/RECORD
