Metadata-Version: 2.1
Name: tulit
Version: 0.4.4
Summary: TULIT - The Universal Legal Informatics Toolkit, is a set of legal informatics utilities collected in a Python package that focuses on the retrieval of legal data and metadata from official sources in the EU, and their transformation in legalJSON, a pythonic data structure for legal documents
License: EUPL 1.2
Author: AlessioNar
Author-email: alessio.nardin@gmail.com
Requires-Python: >=3.11,<4.0
Classifier: License :: Other/Proprietary License
Classifier: Operating System :: OS Independent
Classifier: Programming Language :: Python :: 3
Classifier: Programming Language :: Python :: 3.11
Classifier: Programming Language :: Python :: 3.12
Requires-Dist: beautifulsoup4 (>=4.9.3,<5.0.0)
Requires-Dist: chardet (>=5.2.0,<6.0.0)
Requires-Dist: jsonschema (>=4.24.0,<5.0.0)
Requires-Dist: lxml (>=5.3.0,<6.0.0)
Requires-Dist: pandas (>=2.2.3,<3.0.0)
Requires-Dist: pygments (>=2.19.1,<3.0.0)
Requires-Dist: pytest (>=8.3.3,<9.0.0)
Requires-Dist: requests (>=2.32.3,<3.0.0)
Requires-Dist: sparqlwrapper (>=2.0.0,<3.0.0)
Project-URL: Homepage, https://github.com/AlessioNar/tulit
Project-URL: Issues, https://github.com/AlessioNar/tulit/issues
